[
    {
        "key": "thieuhoang",
        "expiry": "2026-07-26T23:34",
        "type": "vip",
        "device_id": "94220332282765"
    },
    {
        "key": "fhdbsnnsbs",
        "expiry": "2025-09-18T17:19",
        "type": "vip",
        "device_id": "265536542442131"
    }
    {
        "key": "204314575490912",
        "expiry": "2025-09-18T17:31",
        "type": "vip",
        "device_id": "204314575490912"
    },
    {
        "key": "164900369512003",
        "expiry": "2025-09-18T17:31",
        "type": "vip",
        "device_id": "164900369512003"
    },
]






