[
    {
        "key": "thieuhoang",
        "expiry": "2026-07-26T23:34",
        "type": "vip",
        "device_id": "94220332282765"
    },
    {
        "key": "fhdbsnnsbs",
        "expiry": "2025-09-18T17:19",
        "type": "vip",
        "device_id": "265536542442131"
    },
    {
        "key": "204314575490912",
        "expiry": "2025-09-18T17:48",
        "type": "vip",
        "device_id": "204314575490912"
    },
    {
        "key": "164900369512003",
        "expiry": "2025-10-28T21:03",
        "type": "vip",
        "device_id": "164900369512003"
    },
    {
        "key": "tiensang",
        "expiry": "2025-08-04T11:38",
        "type": "vip",
        "device_id": "1213837535233"
    },
    {
        "key": "dinhvip",
        "expiry": "2025-10-02T00:28",
        "type": "vip",
        "device_id": "274753872200580"
    },
    {
        "key": "keyvip",
        "expiry": "2030-07-27T07:33",
        "type": "free",
        "device_id": "197217348723623"
    },
    {
        "key": "vipkey2",
        "expiry": "2025-08-14T18:55",
        "type": "vip",
        "device_id": "179706896388016"
    },
    {
        "key": "toandzcute",
        "expiry": "2025-08-23T18:40",
        "type": "vip",
        "device_id": "125653759881331"
    },
    {
        "key": "vanhieucute",
        "expiry": "2025-09-15T12:43",
        "type": "vip",
        "device_id": "204525464742516"
    },
    {
        "key": "vuvip",
        "expiry": "2025-08-26T08:55",
        "type": "vip",
        "device_id": "79349041340246"
    },
    {
        "key": "246775572575900",
        "expiry": "2025-09-03T13:09",
        "type": "vip",
        "device_id": "246775572575900"
    },
    {
        "key": "baovip",
        "expiry": "2025-09-21T17:06",
        "type": "vip",
        "device_id": "273549557139990"
    },
    {
        "key": "229144647304808",
        "expiry": "2025-09-01T16:58",
        "type": "vip",
        "device_id": "229144647304808"
    },
    {
        "key": "138364567065431",
        "expiry": "2029-08-31T19:47",
        "type": "free",
        "device_id": "138364567065431"
    },
    {
        "key": "214710527680809",
        "expiry": "2025-09-02T19:49",
        "type": "vip",
        "device_id": "214710527680809"
    }
]





